{
  "selected_frame_ids": [
    "im1_f0000",
    "im2_f0000",
    "vid_f0029",
    "vid_f0108",
    "vid_f0000",
    "vid_f0075",
    "vid_f0009",
    "vid_f0052",
    "vid_f0098",
    "vid_f0042",
    "vid_f0087",
    "vid_f0063"
  ],
  "kernel_type": "cosine_l2_normalized_with_epsilon_jitter",
  "method": "dpp_map_greedy_logdet",
  "seed": 0,
  "epsilon": 1e-06,
  "n_keyframes_requested": 10,
  "n_keyframes_selected": 12,
  "num_input_vectors": 134,
  "coverage_extra": 5,
  "input_dir": "/workspace/scan_output/T1-3.3/L/dinov3/all",
  "selected_set_diversity_logdet": -35.75660705566406,
  "selected_set_volume_proxy": 1.72009103391633e-08,
  "coverage_table": [
    {
      "k": 0,
      "selected_frame_ids_prefix": [],
      "coverage": 0.0,
      "delta_coverage": 0.0,
      "diversity_logdet": 0.0,
      "delta_diversity": 0.0,
      "volume_proxy": 0.0
    },
    {
      "k": 1,
      "selected_frame_ids_prefix": [
        "vid_f0029"
      ],
      "coverage": 0.9779679179191589,
      "delta_coverage": 0.9779679179191589,
      "diversity_logdet": 5.364403477869928e-06,
      "delta_diversity": 5.364403477869928e-06,
      "volume_proxy": 1.000002682205336
    },
    {
      "k": 2,
      "selected_frame_ids_prefix": [
        "vid_f0029",
        "vid_f0108"
      ],
      "coverage": 0.9892793297767639,
      "delta_coverage": 0.01131141185760498,
      "diversity_logdet": -1.6299811601638794,
      "delta_diversity": -1.6299865245673573,
      "volume_proxy": 0.442643497007184
    },
    {
      "k": 3,
      "selected_frame_ids_prefix": [
        "vid_f0029",
        "vid_f0108",
        "vid_f0000"
      ],
      "coverage": 0.9900318384170532,
      "delta_coverage": 0.0007525086402893066,
      "diversity_logdet": -4.245654106140137,
      "delta_diversity": -2.6156729459762573,
      "volume_proxy": 0.11969277193601399
    },
    {
      "k": 4,
      "selected_frame_ids_prefix": [
        "vid_f0029",
        "vid_f0108",
        "vid_f0000",
        "vid_f0075"
      ],
      "coverage": 0.991782009601593,
      "delta_coverage": 0.001750171184539795,
      "diversity_logdet": -7.150627136230469,
      "delta_diversity": -2.904973030090332,
      "volume_proxy": 0.028006642407128204
    },
    {
      "k": 5,
      "selected_frame_ids_prefix": [
        "vid_f0029",
        "vid_f0108",
        "vid_f0000",
        "vid_f0075",
        "vid_f0009"
      ],
      "coverage": 0.9923755526542664,
      "delta_coverage": 0.0005935430526733398,
      "diversity_logdet": -10.357182502746582,
      "delta_diversity": -3.2065553665161133,
      "volume_proxy": 0.005635940447928743
    },
    {
      "k": 6,
      "selected_frame_ids_prefix": [
        "vid_f0029",
        "vid_f0108",
        "vid_f0000",
        "vid_f0075",
        "vid_f0009",
        "vid_f0052"
      ],
      "coverage": 0.9931270480155945,
      "delta_coverage": 0.000751495361328125,
      "diversity_logdet": -13.607929229736328,
      "delta_diversity": -3.250746726989746,
      "volume_proxy": 0.001109368200031706
    },
    {
      "k": 7,
      "selected_frame_ids_prefix": [
        "vid_f0029",
        "vid_f0108",
        "vid_f0000",
        "vid_f0075",
        "vid_f0009",
        "vid_f0052",
        "vid_f0098"
      ],
      "coverage": 0.9941621422767639,
      "delta_coverage": 0.0010350942611694336,
      "diversity_logdet": -17.015031814575195,
      "delta_diversity": -3.407102584838867,
      "volume_proxy": 0.00020194485209096586
    },
    {
      "k": 8,
      "selected_frame_ids_prefix": [
        "vid_f0029",
        "vid_f0108",
        "vid_f0000",
        "vid_f0075",
        "vid_f0009",
        "vid_f0052",
        "vid_f0098",
        "vid_f0042"
      ],
      "coverage": 0.9945154786109924,
      "delta_coverage": 0.0003533363342285156,
      "diversity_logdet": -20.62346839904785,
      "delta_diversity": -3.6084365844726562,
      "volume_proxy": 3.324074420051179e-05
    },
    {
      "k": 9,
      "selected_frame_ids_prefix": [
        "vid_f0029",
        "vid_f0108",
        "vid_f0000",
        "vid_f0075",
        "vid_f0009",
        "vid_f0052",
        "vid_f0098",
        "vid_f0042",
        "vid_f0087"
      ],
      "coverage": 0.9949066638946533,
      "delta_coverage": 0.00039118528366088867,
      "diversity_logdet": -24.267017364501953,
      "delta_diversity": -3.6435489654541016,
      "volume_proxy": 5.3763079057365865e-06
    },
    {
      "k": 10,
      "selected_frame_ids_prefix": [
        "vid_f0029",
        "vid_f0108",
        "vid_f0000",
        "vid_f0075",
        "vid_f0009",
        "vid_f0052",
        "vid_f0098",
        "vid_f0042",
        "vid_f0087",
        "vid_f0063"
      ],
      "coverage": 0.9953888654708862,
      "delta_coverage": 0.00048220157623291016,
      "diversity_logdet": -27.952224731445312,
      "delta_diversity": -3.6852073669433594,
      "volume_proxy": 8.516311165033602e-07
    },
    {
      "k": 11,
      "selected_frame_ids_prefix": [
        "vid_f0029",
        "vid_f0108",
        "vid_f0000",
        "vid_f0075",
        "vid_f0009",
        "vid_f0052",
        "vid_f0098",
        "vid_f0042",
        "vid_f0087",
        "vid_f0063",
        "vid_f0093"
      ],
      "coverage": 0.9956675171852112,
      "delta_coverage": 0.00027865171432495117,
      "diversity_logdet": -31.809364318847656,
      "delta_diversity": -3.8571395874023438,
      "volume_proxy": 1.2378964051174556e-07
    },
    {
      "k": 12,
      "selected_frame_ids_prefix": [
        "vid_f0029",
        "vid_f0108",
        "vid_f0000",
        "vid_f0075",
        "vid_f0009",
        "vid_f0052",
        "vid_f0098",
        "vid_f0042",
        "vid_f0087",
        "vid_f0063",
        "vid_f0093",
        "vid_f0004"
      ],
      "coverage": 0.9958935379981995,
      "delta_coverage": 0.00022602081298828125,
      "diversity_logdet": -35.75660705566406,
      "delta_diversity": -3.9472427368164062,
      "volume_proxy": 1.72009103391633e-08
    },
    {
      "k": 13,
      "selected_frame_ids_prefix": [
        "vid_f0029",
        "vid_f0108",
        "vid_f0000",
        "vid_f0075",
        "vid_f0009",
        "vid_f0052",
        "vid_f0098",
        "vid_f0042",
        "vid_f0087",
        "vid_f0063",
        "vid_f0093",
        "vid_f0004",
        "vid_f0036"
      ],
      "coverage": 0.9960833191871643,
      "delta_coverage": 0.00018978118896484375,
      "diversity_logdet": -39.77170944213867,
      "delta_diversity": -4.015102386474609,
      "volume_proxy": 2.3103779269151347e-09
    },
    {
      "k": 14,
      "selected_frame_ids_prefix": [
        "vid_f0029",
        "vid_f0108",
        "vid_f0000",
        "vid_f0075",
        "vid_f0009",
        "vid_f0052",
        "vid_f0098",
        "vid_f0042",
        "vid_f0087",
        "vid_f0063",
        "vid_f0093",
        "vid_f0004",
        "vid_f0036",
        "vid_f0070"
      ],
      "coverage": 0.9962678551673889,
      "delta_coverage": 0.00018453598022460938,
      "diversity_logdet": -43.864349365234375,
      "delta_diversity": -4.092639923095703,
      "volume_proxy": 2.985228362663746e-10
    },
    {
      "k": 15,
      "selected_frame_ids_prefix": [
        "vid_f0029",
        "vid_f0108",
        "vid_f0000",
        "vid_f0075",
        "vid_f0009",
        "vid_f0052",
        "vid_f0098",
        "vid_f0042",
        "vid_f0087",
        "vid_f0063",
        "vid_f0093",
        "vid_f0004",
        "vid_f0036",
        "vid_f0070",
        "vid_f0020"
      ],
      "coverage": 0.996461808681488,
      "delta_coverage": 0.0001939535140991211,
      "diversity_logdet": -47.99276351928711,
      "delta_diversity": -4.128414154052734,
      "volume_proxy": 3.78881862966426e-11
    }
  ]
}
